hubspot3/__init__.py
hubspot3/__main__.py
hubspot3/base.py
hubspot3/blog.py
hubspot3/broadcast.py
hubspot3/cms_files.py
hubspot3/cms_layouts.py
hubspot3/cms_templates.py
hubspot3/companies.py
hubspot3/companies_properties.py
hubspot3/contact_lists.py
hubspot3/contacts.py
hubspot3/crm_association_labels.py
hubspot3/crm_associations.py
hubspot3/crm_pipelines.py
hubspot3/deals.py
hubspot3/ecommerce_bridge.py
hubspot3/email_events.py
hubspot3/email_subscription.py
hubspot3/engagements.py
hubspot3/error.py
hubspot3/forms.py
hubspot3/globals.py
hubspot3/keywords.py
hubspot3/leads.py
hubspot3/lines.py
hubspot3/oauth2.py
hubspot3/owners.py
hubspot3/products.py
hubspot3/properties.py
hubspot3/property_groups.py
hubspot3/prospects.py
hubspot3/settings.py
hubspot3/tickets.py
hubspot3/users.py
hubspot3/utils.py
hubspot3/workflows.py
hubspot3-3.2.56.dist-info/LICENSE
hubspot3-3.2.56.dist-info/METADATA
hubspot3-3.2.56.dist-info/WHEEL
hubspot3-3.2.56.dist-info/entry_points.txt
hubspot3-3.2.56.dist-info/top_level.txt
hubspot3-3.2.56.dist-info/RECORD
