Metadata-Version: 2.1
Name: hubspot3
Version: 3.2.56
Summary: A python wrapper around HubSpot's APIs, for python 3. Built initially around hapipy, but heavily modified.
Home-page: https://github.com/jpetrucciani/hubspot3.git
Download-URL: https://github.com/jpetrucciani/hubspot3.git
Author: HubSpot Dev Team, Jacobi Petrucciani
Author-email: j@cobi.dev
License: LICENSE
Classifier: Programming Language :: Python :: 3
Classifier: Programming Language :: Python :: 3.8
Classifier: Programming Language :: Python :: 3.9
Classifier: Programming Language :: Python :: 3.10
Classifier: Programming Language :: Python :: 3.11
Classifier: Programming Language :: Python :: 3.12
Classifier: Programming Language :: Python :: 3.13
License-File: LICENSE
Requires-Dist: typing-extensions; python_version < "3.8"
Provides-Extra: cli
Requires-Dist: fire==0.4.0; extra == "cli"
